idevision/__init__.py
idevision/async_client.py
idevision/errors.py
idevision/responses.py
idevision/sync_client.py
idevision.py-1.0.10.dist-info/LICENSE
idevision.py-1.0.10.dist-info/METADATA
idevision.py-1.0.10.dist-info/WHEEL
idevision.py-1.0.10.dist-info/top_level.txt
idevision.py-1.0.10.dist-info/RECORD
