Metadata-Version: 2.1
Name: idevision.py
Version: 1.0.10
Summary: A python wrapper for the IDevision api
Home-page: https://github.com/isaa-ctaylor/idevision.py
Author: isaa_ctaylor
Author-email: isaacjontaylor@gmail.com
License: GPL-3.0
Platform: UNKNOWN
Classifier: License :: OSI Approved :: GNU General Public License v3 (GPLv3)
Classifier: Programming Language :: Python :: 3
Classifier: Programming Language :: Python :: 3.8
Classifier: Programming Language :: Python :: 3.9
Requires-Dist: requests (>=2.25.1)
Requires-Dist: aiohttp (>=3.7.4.post0)
